{
	"brand": "Audi",
	"model": "A6 C7",
	"priceStr": "2 760 001 руб.",
	"priceNum": 2760000,
	"volume": 10, 
	"color": "Голубой",
},
{
	"brand": "BMW",
	"model": "3-Series G20",
	"priceStr": "2 720 000 руб.",
	"priceNum": 2720000,
	"volume": 21, 
	"color": "Синий",
},
{
	"brand": "KIA",
	"model": "Cerato",
	"priceStr": "2 760 000 руб.",
	"priceNum": 2760000,
	"volume": 5, 
	"color": "Красный",
},
{
	"brand": "Mazda",
	"model": "Mazda 6",
	"priceStr": "1 567 000 руб.",
	"priceNum": 1567000,
	"volume": 15, 
	"color": "Красный",
},
{
	"brand": "Lada",
	"model": "XRAY Cross",
	"priceStr": "791 900 руб.",
	"priceNum": 791900,
	"volume": 20, 
	"color": "Белый",
},
{
	"brand": "Lada",
	"model": "Largus",
	"priceStr": "795 900 руб.",
	"priceNum": 795900,
	"volume": 56, 
	"color": "Ледниковый",
},
{
	"brand": "Audi",
	"model": "Q8",
	"priceStr": "3 530 000 руб.",
	"priceNum": 3530000,
	"volume": 10, 
	"color": "Лазурно-синий",
},
{
	"brand": "Audi",
	"model": "Q3",
	"priceStr": "1 215 000 руб.",
	"priceNum": 1215000,
	"volume": 3, 
	"color": "Cиний",
},
{
	"brand": "Lexus",
	"model": "LX 450D",
	"priceStr": "6 379 000 руб.",
	"priceNum": 6379000,
	"volume": 2, 
	"color": "Белый",
},
{
	"brand": "Lexus",
	"model": "NX 200",
	"priceStr": "2 599 000 руб.",
	"priceNum": 2599000,
	"volume": 10, 
	"color": "Коричневый металлик",
},
{
	"brand": "DATSUN ",
	"model": "ON-DO",
	"priceStr": "416 000 руб.",
	"priceNum": 416000,
	"volume": 35, 
	"color": "Серебристый",
}
